icn3dpy/__init__.py
icn3dpy/__init__v1.py
icn3dpy/__init__v2.py
icn3dpy/__init__v3.py
icn3dpy-3.47.0.dist-info/LICENSE
icn3dpy-3.47.0.dist-info/METADATA
icn3dpy-3.47.0.dist-info/WHEEL
icn3dpy-3.47.0.dist-info/top_level.txt
icn3dpy-3.47.0.dist-info/RECORD
