Metadata-Version: 2.1
Name: icn3dpy
Version: 3.47.0
Summary: An IPython interface for embedding iCn3D viewer
Home-page: https://github.com/ncbi/icn3d
Author: Jiyao Wang
Author-email: wangjiy@ncbi.lm.nih.gov
License: MIT License
Keywords: WebGL-based protein structure viewer
Platform: UNKNOWN
Classifier: Development Status :: 5 - Production/Stable
Classifier: Intended Audience :: Developers
Classifier: Intended Audience :: Science/Research
Classifier: Topic :: Scientific/Engineering :: Chemistry
Classifier: Topic :: Scientific/Engineering :: Visualization
Classifier: Topic :: Scientific/Engineering :: Bio-Informatics
Classifier: License :: OSI Approved :: MIT License
Classifier: Programming Language :: Python :: 2
Classifier: Programming Language :: Python :: 3
Requires-Dist: idisplay
Requires-Dist: jupyter
